rena/MainWindow.py
rena/__init__.py
rena/config.py
rena/config_signal.py
rena/config_ui.py
rena/load_asset_file.py
rena/main.py
rena/shared.py
rena/startup.py
rena/ui_shared.py
rena/deprecated/__init__.py
rena/examples/BioSemiDummyOutlet.py
rena/examples/ConvertDatsInDirectoryToPickle.py
rena/examples/CreateVideo.py
rena/examples/ExampleScript.py
rena/examples/FrameBoarderTest.py
rena/examples/LSLExampleInlet.py
rena/examples/LSLExampleOutlet.py
rena/examples/LSLExampleOutlet1.py
rena/examples/LSLExampleOutletJohn.py
rena/examples/LSLExampleOutletOscillatory.py
rena/examples/LoadXDF.py
rena/examples/RNStream.py
rena/examples/RNStreamLoadSpeed.py
rena/examples/RNStream_reshape_test.py
rena/examples/RealTimeModelExample.py
rena/examples/SplitterTest.py
rena/examples/SynchronizationTest.py
rena/examples/UdpComms.py
rena/examples/UdpServerExample.py
rena/examples/ZMQClientCameraCapture.py
rena/examples/ZMQExampleOutlet.py
rena/examples/ZMQServerWebCam.py
rena/examples/__init__.py
rena/examples/multiprocess_singleton_test.py
rena/examples/DSP_examples/__init__.py
rena/examples/DSP_examples/notch_test.py
rena/examples/DSP_examples/real_time_notch.py
rena/examples/ObjectDetection/ObjectDetection.py
rena/examples/ObjectDetection/UnityObjectDetection.py
rena/examples/ObjectDetection/__init__.py
rena/examples/OpenBCI_LSL_Matlab_RN_example/OpenBCIInterface.py
rena/examples/OpenBCI_LSL_Matlab_RN_example/__init__.py
rena/exceptions/__init__.py
rena/exceptions/exceptions.py
rena/interfaces/BaseDataStreamInterface.py
rena/interfaces/DataStreamInterface.py
rena/interfaces/InferenceInterface.py
rena/interfaces/LSLInletInterface.py
rena/interfaces/MmWaveSensorLSLInterface.py
rena/interfaces/OpenBCIDeviceInterface.py
rena/interfaces/OpenBCIInterface.py
rena/interfaces/__init__.py
rena/presets/Cmap.py
rena/presets/GroupEntry.py
rena/presets/PlotConfig.py
rena/presets/Presets.py
rena/presets/__init__.py
rena/presets/load_user_preset.py
rena/presets/preset_class_helpers.py
ReNaLabApp-0.0.1.dev14.dist-info/LICENSE
ReNaLabApp-0.0.1.dev14.dist-info/METADATA
ReNaLabApp-0.0.1.dev14.dist-info/WHEEL
ReNaLabApp-0.0.1.dev14.dist-info/top_level.txt
ReNaLabApp-0.0.1.dev14.dist-info/RECORD
